Metadata-Version: 1.0
Name: python-spams
Version: 2.6.1.11
Summary: Python interface for SPAMS
Home-page: http://spams-devel.gforge.inria.fr/
Author: Julien Mairal
Author-email: spams.dev@inria.fr
License: GPLv3
Platform: UNKNOWN
